{
  "id": "co-ley-44-1977",
  "type": "statute",
  "title": "Ley 44 de 1977",
  "short_name": "Ley 44 de 1977",
  "status": "in_force",
  "url": "https://www.funcionpublica.gov.co/eva/gestornormativo/norma.php?i=285",
  "description": "Ley 44 de 1977 Se establece la institución pensional vitalicia",
  "provisions": [
    {
      "provision_ref": "art2",
      "section": "2",
      "title": "Artículo 2",
      "content": "ARTÍCULO 2º. - Esta Ley rige desde su sanción.\n\nREPÚBLICA DE\nCOLOMBIA - GOBIERNO NACIONAL\n\nPUBLÍQUESE Y\nEJECÚTESE\n\nDada en Bogotá,\nD.E., 19 de diciembre de 1977.\n\nEL PRESIDENTE DE LA\nREPÚBLICA,\n\nALFONSO LOPEZ\nMICHELSEN.\n\nEL MINISTRO DE\nTRABAJO Y SEGURIDAD SOCIAL,\n\nOSCAR MONTOYA\nMONTOYA.\n\nNOTA: La presente Ley sustituye el Artículo 8 de la Ley 4 de 1976 en\nmateria de sustitución pensional. Ver artículo 2 Ley 33 de 1973 artículo\n2 Ley 12 de 1975 Artículo\n7 Decreto Nacional\n1160 de 1989\n\nNOTA: Publicado en\nel Diario Oficial No.34940 de diciembre 19 de 1977."
    }
  ],
  "definitions": []
}